panspace/__init__.py
panspace/data_curation.py
panspace/fcgr.py
panspace/index.py
panspace/panspace.py
panspace/stats_assembly.py
panspace/trainer.py
panspace/utils.py
panspace/dataclasses_cli/__init__.py
panspace/dataclasses_cli/activation.py
panspace/dataclasses_cli/autoencoder.py
panspace/dataclasses_cli/loss.py
panspace/dataclasses_cli/metric_learning.py
panspace/dataclasses_cli/optimizer.py
panspace/dataclasses_cli/preprocessing.py
panspace/dnn/__init__.py
panspace/dnn/callbacks.py
panspace/dnn/loaders/__init__.py
panspace/dnn/loaders/autoencoder.py
panspace/dnn/loaders/generator_batches.py
panspace/dnn/loaders/metric_learning.py
panspace/dnn/loaders/utils.py
panspace/dnn/models/__init__.py
panspace/dnn/models/autoencoder_fcgr.py
panspace/dnn/models/cnn_fcgr.py
panspace/dnn/models/cnn_fcgr_dropout.py
panspace/dnn/models/cnn_fcgr_levels.py
panspace/dnn/models/resnet50.py
panspace/dnn/models/custom_layers/__init__.py
panspace/dnn/models/custom_layers/conv_fcgr.py
panspace/dnn/models/custom_layers/deconv_fcgr.py
panspace/dnn/models/custom_layers/euclidean_distance.py
panspace/dnn/utils/__init__.py
panspace/dnn/utils/split_data.py
panspace/dnn/utils/split_data_cross_validation.py
panspace/fcgr_mods/__init__.py
panspace/fcgr_mods/fcgr_from_kmc.py
panspace/fcgr_mods/fcgr_from_tar.py
panspace/fcgr_mods/fcgr_modified.py
panspace/streamlit/__init__.py
panspace/streamlit/app.py
panspace/streamlit/ena.py
panspace/streamlit/html.py
panspace/streamlit/interactive_plot.py
panspace/streamlit/utils.py
panspace-0.2.0.dist-info/licenses/LICENSE
panspace-0.2.0.dist-info/METADATA
panspace-0.2.0.dist-info/WHEEL
panspace-0.2.0.dist-info/entry_points.txt
panspace-0.2.0.dist-info/top_level.txt
panspace-0.2.0.dist-info/RECORD
