Metadata-Version: 2.4
Name: panspace
Version: 0.2.0
Summary: Indexing assemblies with autoencoders and FCGR
Author-email: Jorge Avila Cartes <jorgeavilacartes@gmail.com>
License:                     GNU GENERAL PUBLIC LICENSE
Keywords: index,fcgr,assemblies,bacteria
Classifier: Intended Audience :: Science/Research
Classifier: Topic :: Scientific/Engineering :: Bio-Informatics
Classifier: Programming Language :: Python
License-File: LICENSE
Requires-Dist: typer==0.12.3
Requires-Dist: click==8.1.7
Requires-Dist: scikit-learn==1.3.2
Requires-Dist: cleanlab==2.5.0
Requires-Dist: complexcgr==0.8.0
Requires-Dist: pandas==2.1.4
Requires-Dist: rich==13.7.0
Requires-Dist: rich-argparse==1.4.0
Requires-Dist: tqdm==4.66.1
Requires-Dist: streamlit==1.50.0
Requires-Dist: numpy==1.26.4
Requires-Dist: scipy==1.14.1
Requires-Dist: plotly==6.3.1
Requires-Dist: orjson
Provides-Extra: cpu
Requires-Dist: tensorflow==2.15.1; extra == "cpu"
Requires-Dist: tensorflow-addons==0.23.0; extra == "cpu"
Requires-Dist: tensorflow-probability==0.23.0; extra == "cpu"
Requires-Dist: faiss-cpu==1.7.2; extra == "cpu"
Provides-Extra: gpu
Requires-Dist: tensorflow[and-cuda]==2.15.1; extra == "gpu"
Requires-Dist: tensorflow-addons==0.23.0; extra == "gpu"
Requires-Dist: tensorflow-probability==0.23.0; extra == "gpu"
Requires-Dist: faiss-gpu==1.7.2; extra == "gpu"
Provides-Extra: default
Requires-Dist: panspace[cpu]; extra == "default"
Dynamic: license-file
